MANIFEST.in
setup.cfg
setup.py
cryptoexchange/HttpMD5Util.py
cryptoexchange/OkcoinFutureAPI.py
cryptoexchange/OkcoinSpotAPI.py
cryptoexchange/OkcoinWebsocket.py
cryptoexchange/__init__.py
cryptoexchange/api796.py
cryptoexchange/bitfutures.py
cryptoexchange/bitmex.py
cryptoexchange/bitmex_ws.py
cryptoexchange.egg-info/PKG-INFO
cryptoexchange.egg-info/SOURCES.txt
cryptoexchange.egg-info/dependency_links.txt
cryptoexchange.egg-info/requires.txt
cryptoexchange.egg-info/top_level.txt
cryptoexchange/util/OkcoinClient.py
cryptoexchange/util/bitmex-auth-test.py
cryptoexchange/util/bitmex-generate-api-key.py
cryptoexchange/util/bitmex-ws-auth-test.py