Metadata-Version: 1.0
Name: cryptoexchange
Version: 0.0.6
Summary: API's for bitcoin exchanges
Home-page: https://github.com/joequant/cryptoexchange
Author: Joseph C Wang
Author-email: joequant@gmail.com
License: BSD
Platform: UNKNOWN
